{"root":[{"id":"root","content":"[Review[ Intro to Agile Principles","type":"root","deletable":false,"children":[{"id":"a961151d-8fca-42fd-af63-41f6bebebbd9","content":"prinsip","type":"custom","deletable":true,"children":[{"id":"e7b422c7-093e-4119-b922-fb4119129bbb","content":"aturan dasar menjadi landasan bertindak","type":"custom","deletable":true,"children":[],"width":218,"height":33,"position":{"x":469,"y":0},"depth":2,"link":{"mindmap":{"uuid":""}},"relation":{"name":""}}],"width":144,"height":33,"position":{"x":274,"y":0},"depth":1,"link":{"mindmap":{"uuid":""}},"relation":{"name":""}},{"id":"c9dce790-18bb-4c6a-8dc0-847a2baa5d85","content":"12 prinsip terkait","type":"custom","deletable":true,"children":[{"id":"ef59993e-0250-4782-af90-7b773d7cae5f","content":"our highest is to satisfy customer","type":"custom","deletable":true,"children":[{"id":"0a2d95be-befd-4568-ae55-803aec275f86","content":"produk harus memuaskan customer","type":"custom","deletable":true,"children":[],"width":194,"height":33,"position":{"x":-709,"y":-607.5},"depth":3,"link":{"mindmap":{"uuid":""}},"relation":{"name":""}}],"width":181,"height":33,"position":{"x":-464,"y":-607.5},"depth":2,"link":{"mindmap":{"uuid":""}},"relation":{"name":"1"}},{"id":"2044f1ab-de32-4e0c-9126-a1c73cd64063","content":"throught early and continous delivery of","type":"custom","deletable":true,"children":[],"width":213,"height":33,"position":{"x":-496,"y":-562.5},"depth":2,"link":{"mindmap":{"uuid":""}},"relation":{"name":""}},{"id":"9cd8c3af-b7f9-427b-b151-b13e2c86117c","content":"valuable software","type":"custom","deletable":true,"children":[],"width":144,"height":33,"position":{"x":-427,"y":-517.5},"depth":2,"link":{"mindmap":{"uuid":""}},"relation":{"name":""}},{"id":"2fa64d7f-2191-45c6-9e58-54a4ac3325a5","content":"welcome change requirement even late","type":"custom","deletable":true,"children":[{"id":"4443f4c3-9e26-4563-b66b-ea5da7847461","content":"beradatasi terhadap perubahan dimasa depan","type":"custom","deletable":true,"children":[],"width":244,"height":33,"position":{"x":-788,"y":-472.5},"depth":3,"link":{"mindmap":{"uuid":""}},"relation":{"name":""}}],"width":210,"height":33,"position":{"x":-493,"y":-472.5},"depth":2,"link":{"mindmap":{"uuid":""}},"relation":{"name":"2"}},{"id":"207d90e9-50fe-4c5d-8ce2-da1efbaebcb7","content":"development, agile processes harness change for ","type":"custom","deletable":true,"children":[],"width":263,"height":33,"position":{"x":-546,"y":-427.5},"depth":2,"link":{"mindmap":{"uuid":""}},"relation":{"name":""}},{"id":"77dcc72a-c7a7-4149-a339-867a460fd774","content":"the customer competitive advantage","type":"custom","deletable":true,"children":[],"width":196,"height":33,"position":{"x":-479,"y":-382.5},"depth":2,"link":{"mindmap":{"uuid":""}},"relation":{"name":""}},{"id":"daf87579-5e91-4475-bdab-4827f69e04b5","content":"deliver working software frequenty from a couple","type":"custom","deletable":true,"children":[{"id":"9e809750-4a50-418e-8c3f-728e47b43a51","content":"rilis produk sesering mungkin","type":"custom","deletable":true,"children":[],"width":161,"height":33,"position":{"x":-756,"y":-337.5},"depth":3,"link":{"mindmap":{"uuid":""}},"relation":{"name":""}}],"width":261,"height":33,"position":{"x":-544,"y":-337.5},"depth":2,"link":{"mindmap":{"uuid":""}},"relation":{"name":"3"}},{"id":"bfbd53f7-1464-4d1a-9d58-39413919a614","content":"of week to a couple of mouths with a preference  ","type":"custom","deletable":true,"children":[],"width":255,"height":33,"position":{"x":-538,"y":-292.5},"depth":2,"link":{"mindmap":{"uuid":""}},"relation":{"name":""}},{"id":"5e94edc4-65c2-4366-aab4-3abfd16cbd39","content":"to the shorted timescale","type":"custom","deletable":true,"children":[],"width":144,"height":33,"position":{"x":-427,"y":-247.5},"depth":2,"link":{"mindmap":{"uuid":""}},"relation":{"name":""}},{"id":"23f5a21d-21f7-42c7-96f7-8184cfbda9a0","content":"Business people & developers must work together","type":"custom","deletable":true,"children":[{"id":"b0900b6d-0a86-4c9f-9fdf-c33d78591b79","content":"setiap anggota tim hrs kerjasama walau beda bidang","type":"custom","deletable":true,"children":[],"width":279,"height":33,"position":{"x":-879,"y":-202.5},"depth":3,"link":{"mindmap":{"uuid":""}},"relation":{"name":""}}],"width":266,"height":33,"position":{"x":-549,"y":-202.5},"depth":2,"link":{"mindmap":{"uuid":""}},"relation":{"name":"4"}},{"id":"dcf9dbcf-969f-4cd8-b6c5-6c55b30917bc","content":"daily throughout the project","type":"custom","deletable":true,"children":[],"width":151,"height":33,"position":{"x":-434,"y":-157.5},"depth":2,"link":{"mindmap":{"uuid":""}},"relation":{"name":""}},{"id":"a6ff87e0-d62c-4a24-89e5-2bd69a5452c5","content":"Build project around motivated individuals, give","type":"custom","deletable":true,"children":[{"id":"47a22039-d3b8-43bd-8ba7-bc6226414300","content":"Setiap anggota tim hrs saling suport dan percaya\n","type":"custom","deletable":true,"children":[],"width":260,"height":33,"position":{"x":-846,"y":-112.5},"depth":3,"link":{"mindmap":{"uuid":""}},"relation":{"name":""}}],"width":252,"height":33,"position":{"x":-535,"y":-112.5},"depth":2,"link":{"mindmap":{"uuid":""}},"relation":{"name":"5"}},{"id":"e97f2a40-6a62-4d9d-b85f-7bd196a8357a","content":"them the environment, support the need, trust them","type":"custom","deletable":true,"children":[],"width":273,"height":33,"position":{"x":-556,"y":-67.5},"depth":2,"link":{"mindmap":{"uuid":""}},"relation":{"name":""}},{"id":"4a1440fa-5d61-46e0-92b2-49350bf96e11","content":"to get the job done","type":"custom","deletable":true,"children":[],"width":144,"height":33,"position":{"x":-427,"y":-22.5},"depth":2,"link":{"mindmap":{"uuid":""}},"relation":{"name":""}},{"id":"f66c4516-8a02-4d29-9134-f8c59e058146","content":"Most effective method conveying to development tim","type":"custom","deletable":true,"children":[{"id":"01ec5c22-a922-4336-ac39-c7132c9b8a68","content":"Komunikasi efektif dilakukan secara tatap muka","type":"custom","deletable":true,"children":[],"width":255,"height":33,"position":{"x":-871,"y":22.5},"depth":3,"link":{"mindmap":{"uuid":""}},"relation":{"name":""}}],"width":282,"height":33,"position":{"x":-565,"y":22.5},"depth":2,"link":{"mindmap":{"uuid":""}},"relation":{"name":"6"}},{"id":"a59d7cac-f376-4a53-89bc-bf86815e6b51","content":"is face2face communication","type":"custom","deletable":true,"children":[],"width":155,"height":33,"position":{"x":-438,"y":67.5},"depth":2,"link":{"mindmap":{"uuid":""}},"relation":{"name":""}},{"id":"0d070498-971a-4132-ae88-7b3825f205ac","content":"Working software is primary measure of progress","type":"custom","deletable":true,"children":[{"id":"b47b9074-15a3-4041-b9af-d479bd1c88d5","content":"Progres diukur sbg pengerjaan fitur","type":"custom","deletable":true,"children":[],"width":191,"height":33,"position":{"x":-787,"y":112.5},"depth":3,"link":{"mindmap":{"uuid":""}},"relation":{"name":""}}],"width":262,"height":33,"position":{"x":-545,"y":112.5},"depth":2,"link":{"mindmap":{"uuid":""}},"relation":{"name":"7"}},{"id":"b31d799d-e4f5-4ce2-9e2f-6ed41ef29da6","content":"Agile process promote sustainable development, the","type":"custom","deletable":true,"children":[{"id":"1cff3d7a-1177-4063-9c24-064cb2fcc274","content":"Intensitas pekerjaan hrs dideliver secara konstan","type":"custom","deletable":true,"children":[],"width":260,"height":33,"position":{"x":-872,"y":157.5},"depth":3,"link":{"mindmap":{"uuid":""}},"relation":{"name":""}}],"width":278,"height":33,"position":{"x":-561,"y":157.5},"depth":2,"link":{"mindmap":{"uuid":""}},"relation":{"name":"8"}},{"id":"76cffb3c-f48e-47bc-8518-eb25e864733a","content":"sponsors & user should be able to maintain ","type":"custom","deletable":true,"children":[],"width":230,"height":33,"position":{"x":-513,"y":202.5},"depth":2,"link":{"mindmap":{"uuid":""}},"relation":{"name":""}},{"id":"150c9d50-314b-4a54-8227-9b00ea294d1b","content":"a constant pace indefinitely","type":"custom","deletable":true,"children":[],"width":151,"height":33,"position":{"x":-434,"y":247.5},"depth":2,"link":{"mindmap":{"uuid":""}},"relation":{"name":""}},{"id":"2b2de6b8-b8c5-47ec-a6e0-5b40255dd157","content":"Continuous attention to technical excellence","type":"custom","deletable":true,"children":[{"id":"42c5d1c1-7619-46dd-975a-ea8b4e834739","content":"Kemampuan teknis & design sistem hrs trs dilakukan","type":"custom","deletable":true,"children":[],"width":281,"height":33,"position":{"x":-852,"y":292.5},"depth":3,"link":{"mindmap":{"uuid":""}},"relation":{"name":""}}],"width":237,"height":33,"position":{"x":-520,"y":292.5},"depth":2,"link":{"mindmap":{"uuid":""}},"relation":{"name":"9"}},{"id":"8b9b2dfe-4f87-4b09-bdd8-58107fa89bd3","content":"and good design enhances agility","type":"custom","deletable":true,"children":[],"width":180,"height":33,"position":{"x":-463,"y":337.5},"depth":2,"link":{"mindmap":{"uuid":""}},"relation":{"name":""}},{"id":"78f7abe2-9ee5-40c0-8312-477ee9c24609","content":"Simplicity the art of maximizing the amount of","type":"custom","deletable":true,"children":[{"id":"b8bd6a68-dc4b-4ed3-9626-24bb10f5e323","content":"Proses hrs diisi dgn produktivitas yg diperlukan","type":"custom","deletable":true,"children":[],"width":252,"height":33,"position":{"x":-833,"y":382.5},"depth":3,"link":{"mindmap":{"uuid":""}},"relation":{"name":""}}],"width":247,"height":33,"position":{"x":-530,"y":382.5},"depth":2,"link":{"mindmap":{"uuid":""}},"relation":{"name":"10"}},{"id":"4a09406d-8dbd-4ab8-abb5-022d8484218d","content":"work not done is essential","type":"custom","deletable":true,"children":[],"width":144,"height":33,"position":{"x":-427,"y":427.5},"depth":2,"link":{"mindmap":{"uuid":""}},"relation":{"name":""}},{"id":"bff6179e-52a5-49fd-9ff2-cf58490d8eb8","content":"Best architecture & design emerge from self","type":"custom","deletable":true,"children":[{"id":"50d51c18-4ef9-49c9-8a11-be2f0c9b8d25","content":"Tim mandiri dpt inisiatif tanpa harus diawasi","type":"custom","deletable":true,"children":[],"width":237,"height":33,"position":{"x":-806,"y":472.5},"depth":3,"link":{"mindmap":{"uuid":""}},"relation":{"name":""}}],"width":235,"height":33,"position":{"x":-518,"y":472.5},"depth":2,"link":{"mindmap":{"uuid":""}},"relation":{"name":"11"}},{"id":"6d38e211-059d-4505-a237-b488e5075e6a","content":"organizing teams","type":"custom","deletable":true,"children":[],"width":144,"height":33,"position":{"x":-427,"y":517.5},"depth":2,"link":{"mindmap":{"uuid":""}},"relation":{"name":""}},{"id":"75eea0db-54a4-4500-a596-3610313a9833","content":"At regular intervals team reflects on how to becom","type":"custom","deletable":true,"children":[{"id":"be2a85a9-57cb-4356-8e6b-c87be2292b41","content":"Tim hrs selalu refleksi dan evaluasi","type":"custom","deletable":true,"children":[],"width":190,"height":33,"position":{"x":-792,"y":562.5},"depth":3,"link":{"mindmap":{"uuid":""}},"relation":{"name":""}}],"width":268,"height":33,"position":{"x":-551,"y":562.5},"depth":2,"link":{"mindmap":{"uuid":""}},"relation":{"name":""}},{"id":"097353d6-78e3-4c2b-adda-d9f48f31d706","content":"more effective then tunes adjust its behavior","type":"custom","deletable":true,"children":[],"width":238,"height":33,"position":{"x":-521,"y":607.5},"depth":2,"link":{"mindmap":{"uuid":""}},"relation":{"name":"12"}}],"width":144,"height":33,"position":{"x":-195,"y":0},"depth":1,"link":{"mindmap":{"uuid":""}},"relation":{"name":""}}],"width":223,"height":33,"position":{"x":0,"y":0},"depth":0,"link":{"mindmap":{"uuid":""}}}],"version":2}