{"root":[{"id":"root","content":"[Review] Indikasi Agile Mindset Terinstall Sempurna","type":"root","deletable":false,"children":[{"id":"73ea598e-7ab8-4219-9709-cb99748e8132","content":"agile manifesto","type":"custom","deletable":true,"children":[{"id":"61ce7aa6-3ed7-4e8b-a740-85aaf64113b9","content":"individual&interactions","type":"custom","deletable":true,"children":[{"id":"b8e4fb5d-0407-4f79-bf48-4d3f7d363327","content":"menjaga tim yg baik","type":"custom","deletable":true,"children":[],"width":145,"height":34,"position":{"x":773,"y":-247.5},"depth":3,"link":{"mindmap":{"uuid":""}},"relation":{"name":""}},{"id":"c8057020-9939-4521-8c06-bb4eadc4113d","content":"mendahulukan keberhasilan tim","type":"custom","deletable":true,"children":[],"width":161,"height":34,"position":{"x":773,"y":-202.5},"depth":3,"link":{"mindmap":{"uuid":""}},"relation":{"name":""}},{"id":"1fc17c3f-c76b-4870-833f-e24dc784ed24","content":"ketika terjadi kegagalan yg dievaluasi adl tim","type":"custom","deletable":true,"children":[],"width":222,"height":34,"position":{"x":773,"y":-157.5},"depth":3,"link":{"mindmap":{"uuid":""}},"relation":{"name":""}}],"width":145,"height":34,"position":{"x":575,"y":-202.5},"depth":2,"link":{"mindmap":{"uuid":""}},"relation":{"name":""}},{"id":"ce2d69c8-88ba-4f11-bbfe-ef78c90e3c13","content":"working software","type":"custom","deletable":true,"children":[{"id":"8c7d7e04-ebe7-4bc3-8037-35bbb43b657c","content":"saran kritik menjadi sarana perbaikan","type":"custom","deletable":true,"children":[],"width":187,"height":34,"position":{"x":773,"y":-112.5},"depth":3,"link":{"mindmap":{"uuid":""}},"relation":{"name":""}},{"id":"d7d6b147-0d7d-45e5-8cf4-46449c02f424","content":"memiliki output nyata mengenai apa yg telah dikemb","type":"custom","deletable":true,"children":[],"width":259,"height":34,"position":{"x":773,"y":-67.5},"depth":3,"link":{"mindmap":{"uuid":""}},"relation":{"name":""}},{"id":"0e3e2bbf-f1d7-422c-8820-3d3c6b22f104","content":"tdk melihat kegagalan sbg aib","type":"custom","deletable":true,"children":[],"width":151,"height":34,"position":{"x":773,"y":-22.5},"depth":3,"link":{"mindmap":{"uuid":""}},"relation":{"name":""}}],"width":145,"height":34,"position":{"x":575,"y":-67.5},"depth":2,"link":{"mindmap":{"uuid":""}},"relation":{"name":""}},{"id":"a85513e7-bfb1-4057-b440-dac4c69bfa36","content":"customer collaboration","type":"custom","deletable":true,"children":[{"id":"26a604ba-7784-45bd-9fb0-54b8b3f5e47d","content":"selalu melakukan validasi ke user","type":"custom","deletable":true,"children":[],"width":169,"height":34,"position":{"x":773,"y":22.5},"depth":3,"link":{"mindmap":{"uuid":""}},"relation":{"name":""}},{"id":"9b9803e6-87f9-4539-a051-c820b720c5fb","content":"mendahulukan preferensi user","type":"custom","deletable":true,"children":[],"width":154,"height":34,"position":{"x":773,"y":67.5},"depth":3,"link":{"mindmap":{"uuid":""}},"relation":{"name":""}},{"id":"03e93cba-3460-471b-bff7-d7351e235872","content":"mengambil langkah berdasarkan data","type":"custom","deletable":true,"children":[],"width":188,"height":34,"position":{"x":773,"y":112.5},"depth":3,"link":{"mindmap":{"uuid":""}},"relation":{"name":""}}],"width":145,"height":34,"position":{"x":575,"y":67.5},"depth":2,"link":{"mindmap":{"uuid":""}},"relation":{"name":""}},{"id":"db8ddfb4-282b-4571-9657-535d0a1f4b59","content":"responding to change","type":"custom","deletable":true,"children":[{"id":"913fdf5b-bb58-4984-8518-8e2e136f98ab","content":"melihat masalah sbg rasa syukur","type":"custom","deletable":true,"children":[],"width":165,"height":34,"position":{"x":773,"y":157.5},"depth":3,"link":{"mindmap":{"uuid":""}},"relation":{"name":""}},{"id":"471f3581-4ff5-4392-94e8-6af988b043f4","content":"melihat perubahan tren pasar","type":"custom","deletable":true,"children":[],"width":149,"height":34,"position":{"x":773,"y":202.5},"depth":3,"link":{"mindmap":{"uuid":""}},"relation":{"name":""}},{"id":"5811ac6c-25fd-4a44-9099-2ba5912f165c","content":"tdk khawatir atas keberadaan kompetitor","type":"custom","deletable":true,"children":[],"width":203,"height":34,"position":{"x":773,"y":247.5},"depth":3,"link":{"mindmap":{"uuid":""}},"relation":{"name":""}}],"width":145,"height":34,"position":{"x":575,"y":202.5},"depth":2,"link":{"mindmap":{"uuid":""}},"relation":{"name":""}}],"width":145,"height":34,"position":{"x":376,"y":0},"depth":1,"link":{"mindmap":{"uuid":""}},"relation":{"name":""}}],"width":325,"height":34,"position":{"x":0,"y":0},"depth":0,"link":{"mindmap":{"uuid":""}}}],"version":3}