{"root":[{"id":"root","content":"Kunci Kesuksesan Agile Transformation","type":"root","deletable":false,"children":[{"id":"d398eebf-1d17-4c35-a8b5-b25cc83be98c","content":"Bertahap","type":"custom","deletable":true,"children":[{"id":"22923a33-0170-448a-a093-358d6783b8b3","content":"Tahap-tahap agile","type":"custom","deletable":true,"children":[{"id":"059c02ca-305e-4761-b8b3-c72b11a91e8e","content":"Agile Onion","type":"custom","deletable":true,"children":[{"id":"f0af9d64-1440-4635-aceb-1566dfc2db63","content":"1.Agile Mindset","type":"custom","deletable":true,"children":[],"width":145,"height":34,"position":{"x":917,"y":-112.5},"depth":4,"link":{"mindmap":{"uuid":""}},"relation":{"name":""}},{"id":"0cb4b978-7248-4081-908a-f5363ab013d8","content":"2.Value ","type":"custom","deletable":true,"children":[],"width":145,"height":34,"position":{"x":917,"y":-67.5},"depth":4,"link":{"mindmap":{"uuid":""}},"relation":{"name":""}},{"id":"61b651cc-65ff-4b2e-ab31-3aeba6c65614","content":"3.principles","type":"custom","deletable":true,"children":[],"width":145,"height":34,"position":{"x":917,"y":-22.5},"depth":4,"link":{"mindmap":{"uuid":""}},"relation":{"name":""}},{"id":"659a3ea9-eeee-4712-8ea7-90d021d9475e","content":"4.principles","type":"custom","deletable":true,"children":[],"width":145,"height":34,"position":{"x":917,"y":22.5},"depth":4,"link":{"mindmap":{"uuid":""}},"relation":{"name":""}},{"id":"3ac8ffa9-9e89-4aa4-971b-dec0fb1400ce","content":"5.tools and process.","type":"custom","deletable":true,"children":[],"width":145,"height":34,"position":{"x":917,"y":67.5},"depth":4,"link":{"mindmap":{"uuid":""}},"relation":{"name":""}}],"width":145,"height":34,"position":{"x":717,"y":-22.5},"depth":3,"link":{"mindmap":{"uuid":""}},"relation":{"name":""}}],"width":145,"height":34,"position":{"x":521,"y":-22.5},"depth":2,"link":{"mindmap":{"uuid":""}},"relation":{"name":""}}],"width":145,"height":34,"position":{"x":325,"y":-22.5},"depth":1,"link":{"mindmap":{"uuid":""}},"relation":{"name":""}},{"id":"9015ca62-4db7-41b4-a46b-67fd07ae078f","content":"Don't ","type":"custom","deletable":true,"children":[{"id":"fdaab6c7-7a5f-4747-988c-e03531df1094","content":"Langsung ke tools and process","type":"custom","deletable":true,"children":[],"width":169,"height":34,"position":{"x":521,"y":112.5},"depth":2,"link":{"mindmap":{"uuid":""}},"relation":{"name":""}}],"width":145,"height":34,"position":{"x":325,"y":112.5},"depth":1,"link":{"mindmap":{"uuid":""}},"relation":{"name":""}}],"width":273,"height":34,"position":{"x":0,"y":0},"depth":0,"link":{"mindmap":{"uuid":""}}}],"version":3}