{"root":[{"id":"root","content":"Kunci Kesuksesan Agile Transformation","type":"root","deletable":false,"children":[{"id":"a459d620-5429-4f7b-afb4-ed55ba893a02","content":"Agile Onion","type":"custom","deletable":true,"children":[{"id":"d7df0aa9-d56d-469d-99a3-8f40ca250745","content":"change less often","type":"custom","deletable":true,"children":[],"width":145,"height":34,"position":{"x":523,"y":-67.5},"depth":2,"link":{"mindmap":{"uuid":""}},"relation":{"name":""}},{"id":"f29b8a37-32c9-4271-b4ed-dfd385e1ac0a","content":"less visible, more powerful","type":"custom","deletable":true,"children":[],"width":147,"height":34,"position":{"x":523,"y":-22.5},"depth":2,"link":{"mindmap":{"uuid":""}},"relation":{"name":""}},{"id":"5fd0c9b9-24f3-4744-8b27-990521430827","content":"more visible, less powerful","type":"custom","deletable":true,"children":[],"width":147,"height":34,"position":{"x":523,"y":22.5},"depth":2,"link":{"mindmap":{"uuid":""}},"relation":{"name":""}},{"id":"bb4ca801-8b47-4b6d-8c32-feb91ea62cb3","content":"dynamic change more often","type":"custom","deletable":true,"children":[],"width":153,"height":34,"position":{"x":523,"y":67.5},"depth":2,"link":{"mindmap":{"uuid":""}},"relation":{"name":""}}],"width":145,"height":34,"position":{"x":324,"y":0},"depth":1,"link":{"mindmap":{"uuid":""}},"relation":{"name":""}}],"width":273,"height":34,"position":{"x":0,"y":0},"depth":0,"link":{"mindmap":{"uuid":""}}}],"version":2}