{"root":[{"id":"root","content":"Agile Onion","type":"root","deletable":false,"children":[{"id":"291c4080-556f-41f0-95c5-618c0adae798","content":"Mindset","type":"custom","deletable":true,"children":[{"id":"c33a52da-e5e5-406a-b8b2-27dd2233e52c","content":"Growth mindset","type":"custom","deletable":true,"children":[],"width":145,"height":34,"position":{"x":394,"y":-45},"depth":2,"link":{"mindmap":{"uuid":""}},"relation":{"name":""}}],"width":145,"height":34,"position":{"x":198,"y":-45},"depth":1,"link":{"mindmap":{"uuid":""}},"relation":{"name":""}},{"id":"19c54cc1-9864-49f0-9e66-19015f41414c","content":"Values","type":"custom","deletable":true,"children":[{"id":"8434c751-811d-4e14-a658-b3a9344d6396","content":"Agile manifesto","type":"custom","deletable":true,"children":[{"id":"a5867ea0-e2c7-48a8-9b02-55f72d79d4af","content":"Respon terhadap perubahan","type":"custom","deletable":true,"children":[],"width":155,"height":34,"position":{"x":590,"y":0},"depth":3,"link":{"mindmap":{"uuid":""}},"relation":{"name":""}}],"width":145,"height":34,"position":{"x":394,"y":0},"depth":2,"link":{"mindmap":{"uuid":""}},"relation":{"name":""}}],"width":145,"height":34,"position":{"x":198,"y":0},"depth":1,"link":{"mindmap":{"uuid":""}},"relation":{"name":""}},{"id":"843f5578-c6b2-4b7a-be53-ba85c26928ff","content":"Prinsip","type":"custom","deletable":true,"children":[{"id":"3bcc1877-8bc7-4ccb-9226-52a965a77bd2","content":"Budaya kerja dari tim","type":"custom","deletable":true,"children":[],"width":145,"height":34,"position":{"x":394,"y":45},"depth":2,"link":{"mindmap":{"uuid":""}},"relation":{"name":""}}],"width":145,"height":34,"position":{"x":198,"y":45},"depth":1,"link":{"mindmap":{"uuid":""}},"relation":{"name":""}},{"id":"851f5ca4-9139-42d8-96b2-12bdc32965a2","content":"Praktik","type":"custom","deletable":true,"children":[{"id":"52569434-d20f-42dd-ad40-eefc21b6c086","content":"Praktik yang diadopsi pada framework agile","type":"custom","deletable":true,"children":[],"width":234,"height":34,"position":{"x":-482,"y":-22.5},"depth":2,"link":{"mindmap":{"uuid":""}},"relation":{"name":""}}],"width":145,"height":34,"position":{"x":-197,"y":-22.5},"depth":1,"link":{"mindmap":{"uuid":""}},"relation":{"name":""}},{"id":"e73ece3f-afeb-4ef8-9818-1c65afec17d8","content":"Tools & Process","type":"custom","deletable":true,"children":[{"id":"90c36a5b-86cc-482f-8c97-52c5a578b27d","content":"Teknologi yang digunakan","type":"custom","deletable":true,"children":[],"width":145,"height":34,"position":{"x":-393,"y":22.5},"depth":2,"link":{"mindmap":{"uuid":""}},"relation":{"name":""}}],"width":145,"height":34,"position":{"x":-197,"y":22.5},"depth":1,"link":{"mindmap":{"uuid":""}},"relation":{"name":""}}],"width":145,"height":34,"position":{"x":0,"y":0},"depth":0,"link":{"mindmap":{"uuid":""}}}],"version":5}