{"root":[{"id":"root","content":"[Coaching] Process Impediments Review #3","type":"root","deletable":false,"children":[{"id":"2aea200a-3a17-4f13-bea5-cab0c0fe6e1c","content":"Miker","type":"custom","deletable":true,"children":[{"id":"c8ca11ed-8b44-40ca-8727-8b3753bf3531","content":"Muda (Non value added)","type":"custom","deletable":true,"children":[{"id":"4c0bc789-24d5-4fc2-933a-356a398a6982","content":"Disaat scrum ada yang bermain game","type":"custom","deletable":true,"children":[],"width":247,"height":34,"position":{"x":-716,"y":-202.5},"depth":3,"link":{"mindmap":{"uuid":""}},"relation":{"name":""}}],"width":164,"height":34,"position":{"x":-418,"y":-202.5},"depth":2,"link":{"mindmap":{"uuid":""}},"relation":{"name":""}}],"width":145,"height":34,"position":{"x":-203,"y":-202.5},"depth":1,"link":{"mindmap":{"uuid":""}},"relation":{"name":""}},{"id":"96a54228-d55f-4f2b-88e5-acee6d3e762a","content":"Journey map","type":"custom","deletable":true,"children":[{"id":"860f4f77-ff01-4d30-a93c-5b500493629c","content":"Overproduction","type":"custom","deletable":true,"children":[{"id":"37f1da0c-0306-4a49-a8ba-5e6f0cba98e9","content":"Membuat radius tetapi tidak terpakai","type":"custom","deletable":true,"children":[],"width":242,"height":34,"position":{"x":-692,"y":-157.5},"depth":3,"link":{"mindmap":{"uuid":""}},"relation":{"name":""}}],"width":145,"height":34,"position":{"x":-399,"y":-157.5},"depth":2,"link":{"mindmap":{"uuid":""}},"relation":{"name":""}}],"width":145,"height":34,"position":{"x":-203,"y":-157.5},"depth":1,"link":{"mindmap":{"uuid":""}},"relation":{"name":""}},{"id":"4eef6e51-d04d-4247-a8a4-0b973c035a46","content":"Countlorie","type":"custom","deletable":true,"children":[{"id":"05063641-288f-46cf-af2b-b579dc524524","content":"Muri (Overburden)","type":"custom","deletable":true,"children":[{"id":"2777a38c-a41a-4de7-999e-74a05d8b4b40","content":"Saat sprint 2 ada anak yang mengambil task banyak","type":"custom","deletable":true,"children":[],"width":337,"height":34,"position":{"x":-787,"y":-112.5},"depth":3,"link":{"mindmap":{"uuid":""}},"relation":{"name":""}}],"width":145,"height":34,"position":{"x":-399,"y":-112.5},"depth":2,"link":{"mindmap":{"uuid":""}},"relation":{"name":""}}],"width":145,"height":34,"position":{"x":-203,"y":-112.5},"depth":1,"link":{"mindmap":{"uuid":""}},"relation":{"name":""}},{"id":"ee3f984e-68c7-4b10-a914-ddf3496ebed8","content":"goAT","type":"custom","deletable":true,"children":[{"id":"1529a1fc-98ff-458e-a970-2e2152c8b32f","content":"Non Utilized Talent","type":"custom","deletable":true,"children":[{"id":"609c1b90-6d3a-427c-8266-92e11778cab0","content":"Belajar react terlebih dahulu sehingga ","type":"custom","deletable":true,"children":[{"id":"d9cbd4d5-8f59-4c61-881e-59351a50d877","content":"teman tim tidak dapat maksimal kerjanya","type":"custom","deletable":true,"children":[],"width":270,"height":34,"position":{"x":-1020,"y":-67.5},"depth":4,"link":{"mindmap":{"uuid":""}},"relation":{"name":""}}],"width":249,"height":34,"position":{"x":-699,"y":-67.5},"depth":3,"link":{"mindmap":{"uuid":""}},"relation":{"name":""}}],"width":145,"height":34,"position":{"x":-399,"y":-67.5},"depth":2,"link":{"mindmap":{"uuid":""}},"relation":{"name":""}}],"width":145,"height":34,"position":{"x":-203,"y":-67.5},"depth":1,"link":{"mindmap":{"uuid":""}},"relation":{"name":""}},{"id":"73d901fb-6599-4c0d-a506-875c4edbcdce","content":"Laras","type":"custom","deletable":true,"children":[{"id":"ef5b3481-1ff0-446d-b8bc-64f8aa63b6dd","content":"Waiting","type":"custom","deletable":true,"children":[{"id":"1da05598-685b-4252-a99b-d286f0f50ed5","content":"Frontend harus menunggu BackEnd","type":"custom","deletable":true,"children":[{"id":"f0ab235f-7c02-4a60-8c11-7d2376147170","content":"Agar dapat hit API","type":"custom","deletable":true,"children":[],"width":145,"height":34,"position":{"x":-880,"y":-22.5},"depth":4,"link":{"mindmap":{"uuid":""}},"relation":{"name":""}}],"width":234,"height":34,"position":{"x":-684,"y":-22.5},"depth":3,"link":{"mindmap":{"uuid":""}},"relation":{"name":""}}],"width":145,"height":34,"position":{"x":-399,"y":-22.5},"depth":2,"link":{"mindmap":{"uuid":""}},"relation":{"name":""}}],"width":145,"height":34,"position":{"x":-203,"y":-22.5},"depth":1,"link":{"mindmap":{"uuid":""}},"relation":{"name":""}},{"id":"451c4621-4935-4d08-b0f4-784aafd09c6a","content":"Smilearn","type":"custom","deletable":true,"children":[{"id":"44d47e70-a0a7-44ed-a9fc-24b35eabd840","content":"Non Utilized Talent","type":"custom","deletable":true,"children":[{"id":"9b72e63b-f53f-4b01-909d-ef610465edf8","content":"Developer harus belajar dulu saat dev web","type":"custom","deletable":true,"children":[],"width":276,"height":34,"position":{"x":-727,"y":22.5},"depth":3,"link":{"mindmap":{"uuid":""}},"relation":{"name":""}}],"width":145,"height":34,"position":{"x":-400,"y":22.5},"depth":2,"link":{"mindmap":{"uuid":""}},"relation":{"name":""}},{"id":"6ff877fb-73bb-465b-85cf-3760edb9c21e","content":"Motion","type":"custom","deletable":true,"children":[{"id":"c6cb3084-bccc-46f0-9db1-3fcc1999911e","content":"Saat mengerjakan backlog pindah ke task lain","type":"custom","deletable":true,"children":[],"width":299,"height":34,"position":{"x":-750,"y":67.5},"depth":3,"link":{"mindmap":{"uuid":""}},"relation":{"name":""}}],"width":145,"height":34,"position":{"x":-400,"y":67.5},"depth":2,"link":{"mindmap":{"uuid":""}},"relation":{"name":""}}],"width":145,"height":34,"position":{"x":-203,"y":45},"depth":1,"link":{"mindmap":{"uuid":""}},"relation":{"name":""}},{"id":"06ef5637-1424-4952-86c5-b5fe6cc28732","content":"Remi","type":"custom","deletable":true,"children":[{"id":"6d44bebe-bfb5-4d50-a91d-d2a4c24ef68f","content":"Defect","type":"custom","deletable":true,"children":[{"id":"d273bea6-40e1-4091-91df-fdec8bb303b4","content":"Saat alarm di swipe ke atas malah white screen","type":"custom","deletable":true,"children":[],"width":308,"height":34,"position":{"x":-759,"y":112.5},"depth":3,"link":{"mindmap":{"uuid":""}},"relation":{"name":""}}],"width":145,"height":34,"position":{"x":-400,"y":112.5},"depth":2,"link":{"mindmap":{"uuid":""}},"relation":{"name":""}},{"id":"25615fea-0436-4891-be7b-492e9e9f7eb8","content":"Defect","type":"custom","deletable":true,"children":[{"id":"a5285f7b-903e-4529-853a-d503dddcbf16","content":"Banyak fitur library yang bisa dipelajari","type":"custom","deletable":true,"children":[{"id":"39397589-1c2b-4c07-8019-850821de45d6","content":"tapi tidak digunakan","type":"custom","deletable":true,"children":[],"width":145,"height":34,"position":{"x":-902,"y":157.5},"depth":4,"link":{"mindmap":{"uuid":""}},"relation":{"name":""}}],"width":255,"height":34,"position":{"x":-706,"y":157.5},"depth":3,"link":{"mindmap":{"uuid":""}},"relation":{"name":""}}],"width":145,"height":34,"position":{"x":-400,"y":157.5},"depth":2,"link":{"mindmap":{"uuid":""}},"relation":{"name":""}}],"width":145,"height":34,"position":{"x":-203,"y":135},"depth":1,"link":{"mindmap":{"uuid":""}},"relation":{"name":""}},{"id":"8dcb966f-7c9c-4be9-bd03-9d0fc7de9ff1","content":"mealty","type":"custom","deletable":true,"children":[{"id":"46a64074-ef36-4e71-a121-2a4e478b1c89","content":"Divergent Goals","type":"custom","deletable":true,"children":[{"id":"5533716f-cb77-4162-8c03-986d5a4ee72f","content":"Anggota lain mengikuti himpunan","type":"custom","deletable":true,"children":[],"width":222,"height":34,"position":{"x":-683,"y":202.5},"depth":3,"link":{"mindmap":{"uuid":""}},"relation":{"name":""}}],"width":145,"height":34,"position":{"x":-399,"y":202.5},"depth":2,"link":{"mindmap":{"uuid":""}},"relation":{"name":""}}],"width":145,"height":34,"position":{"x":-203,"y":202.5},"depth":1,"link":{"mindmap":{"uuid":""}},"relation":{"name":""}}],"width":299,"height":34,"position":{"x":0,"y":0},"depth":0,"link":{"mindmap":{"uuid":""}}}],"version":3}