{"root":[{"id":"root","content":"Lean Thinking dan MVP","type":"root","deletable":false,"children":[{"id":"bd330c8b-15e7-4c13-ab6b-5a8dcf8c1e79","content":"Mindset","type":"custom","deletable":true,"children":[{"id":"4e6ff132-fbfe-4e81-a29a-e088ed9061e3","content":"Growth mindset","type":"custom","deletable":true,"children":[{"id":"cc72ee2e-7577-41ea-8314-fcd6d0806e09","content":"kegagalan bukanlah sebuah aib","type":"custom","deletable":true,"children":[],"width":170,"height":33,"position":{"x":611,"y":-202.5},"depth":3,"link":{"mindmap":{"uuid":""}},"relation":{"name":""}}],"width":144,"height":33,"position":{"x":416,"y":-202.5},"depth":2,"link":{"mindmap":{"uuid":""}},"relation":{"name":""}},{"id":"e62efe65-3c35-4302-b045-deab7d418f2b","content":"fixed mindset","type":"custom","deletable":true,"children":[{"id":"62bbde05-4f02-4949-87c6-78850d09c6da","content":"Kegagalan adalah sebuah aib","type":"custom","deletable":true,"children":[],"width":159,"height":33,"position":{"x":611,"y":-157.5},"depth":3,"link":{"mindmap":{"uuid":""}},"relation":{"name":""}}],"width":144,"height":33,"position":{"x":416,"y":-157.5},"depth":2,"link":{"mindmap":{"uuid":""}},"relation":{"name":""}}],"width":144,"height":33,"position":{"x":220,"y":-180},"depth":1,"link":{"mindmap":{"uuid":""}},"relation":{"name":""}},{"id":"ceb1c2e5-98c2-4e6e-a5cb-b8ea8044d37a","content":"Values","type":"custom","deletable":true,"children":[{"id":"71f2c3d6-64ab-410a-85f7-006b2a7f2bba","content":"individual and interactions","type":"custom","deletable":true,"children":[{"id":"fc8bd1bb-0dd7-43d4-aeae-60e5d8c1f355","content":"fokus pada people","type":"custom","deletable":true,"children":[],"width":144,"height":33,"position":{"x":614,"y":-112.5},"depth":3,"link":{"mindmap":{"uuid":""}},"relation":{"name":""}}],"width":145,"height":33,"position":{"x":418,"y":-112.5},"depth":2,"link":{"mindmap":{"uuid":""}},"relation":{"name":""}},{"id":"074f4e10-9964-42cb-ae13-1339fd0f20bc","content":"working software","type":"custom","deletable":true,"children":[{"id":"a8c050cd-5428-4559-8256-aae45f7b4ff5","content":"mengembangkan product","type":"custom","deletable":true,"children":[],"width":144,"height":33,"position":{"x":614,"y":-67.5},"depth":3,"link":{"mindmap":{"uuid":""}},"relation":{"name":""}},{"id":"9a8e968d-1be4-40cb-806f-d60495b9212d","content":"product yang di deliver","type":"custom","deletable":true,"children":[],"width":144,"height":33,"position":{"x":614,"y":-22.5},"depth":3,"link":{"mindmap":{"uuid":""}},"relation":{"name":""}}],"width":144,"height":33,"position":{"x":418,"y":-45},"depth":2,"link":{"mindmap":{"uuid":""}},"relation":{"name":""}},{"id":"7b472f1a-448e-4758-b007-35e8092e9e3c","content":"Customer collaboration","type":"custom","deletable":true,"children":[],"width":144,"height":33,"position":{"x":418,"y":22.5},"depth":2,"link":{"mindmap":{"uuid":""}},"relation":{"name":""}},{"id":"2c32cd34-4535-471f-856e-43ea02f60c1c","content":"Responding to change","type":"custom","deletable":true,"children":[],"width":144,"height":33,"position":{"x":418,"y":67.5},"depth":2,"link":{"mindmap":{"uuid":""}},"relation":{"name":""}}],"width":144,"height":33,"position":{"x":220,"y":-16.875},"depth":1,"link":{"mindmap":{"uuid":""}},"relation":{"name":""}},{"id":"ed035c94-7d9f-44f5-a0c6-3b8045eecf6e","content":"Principles","type":"custom","deletable":true,"children":[],"width":144,"height":33,"position":{"x":220,"y":112.5},"depth":1,"link":{"mindmap":{"uuid":""}},"relation":{"name":""}},{"id":"f787eab2-aa43-4175-95f0-6482c55e965a","content":"Iterative incremental","type":"custom","deletable":true,"children":[{"id":"dde1efb8-fabb-4ec9-ab2a-2f7ce5c7acba","content":"iterative","type":"custom","deletable":true,"children":[{"id":"fad7505c-d06d-46f6-8ed1-160c28f960ee","content":"continues improvement","type":"custom","deletable":true,"children":[],"width":144,"height":33,"position":{"x":611,"y":157.5},"depth":3,"link":{"mindmap":{"uuid":""}},"relation":{"name":""}}],"width":144,"height":33,"position":{"x":416,"y":157.5},"depth":2,"link":{"mindmap":{"uuid":""}},"relation":{"name":""}},{"id":"e72350b7-ae0e-4b31-a95f-189e150b086f","content":"incremental","type":"custom","deletable":true,"children":[{"id":"6cda0b23-4496-434e-b69c-324f2da9c7d4","content":"early delivery","type":"custom","deletable":true,"children":[],"width":144,"height":33,"position":{"x":611,"y":202.5},"depth":3,"link":{"mindmap":{"uuid":""}},"relation":{"name":""}}],"width":144,"height":33,"position":{"x":416,"y":202.5},"depth":2,"link":{"mindmap":{"uuid":""}},"relation":{"name":""}}],"width":144,"height":33,"position":{"x":220,"y":180},"depth":1,"link":{"mindmap":{"uuid":""}},"relation":{"name":""}},{"id":"7e9633ad-6e5b-4d7f-a02f-2a7f40fa61d0","content":"agile vs lean","type":"custom","deletable":true,"children":[{"id":"a485a72c-8cd0-49d8-9da2-6ad6ad45a267","content":"agile","type":"custom","deletable":true,"children":[{"id":"75939fa2-970a-4b05-83db-15e2c615eb88","content":"Value creation","type":"custom","deletable":true,"children":[],"width":144,"height":33,"position":{"x":-588,"y":-135},"depth":3,"link":{"mindmap":{"uuid":""}},"relation":{"name":""}}],"width":144,"height":33,"position":{"x":-393,"y":-135},"depth":2,"link":{"mindmap":{"uuid":""}},"relation":{"name":""}},{"id":"e2c81e34-2bfe-4bc4-909c-374eb25c8c84","content":"lean","type":"custom","deletable":true,"children":[{"id":"44c6827a-9b2c-47fb-8571-142d6fbb888e","content":"Waste removal","type":"custom","deletable":true,"children":[{"id":"6ea48d7e-22b1-49dc-b467-d75eacd8a329","content":"Segala bentuk kesiasiaan khususnya dalam resource","type":"custom","deletable":true,"children":[],"width":280,"height":33,"position":{"x":-920,"y":-90},"depth":4,"link":{"mindmap":{"uuid":""}},"relation":{"name":""}},{"id":"883bccc8-6e12-4d9a-9789-69e5b148778f","content":"misalnya penggunaan waktu, dana, dan energi","type":"custom","deletable":true,"children":[],"width":245,"height":33,"position":{"x":-885,"y":-45},"depth":4,"link":{"mindmap":{"uuid":""}},"relation":{"name":""}}],"width":144,"height":33,"position":{"x":-588,"y":-67.5},"depth":3,"link":{"mindmap":{"uuid":""}},"relation":{"name":""}}],"width":144,"height":33,"position":{"x":-393,"y":-67.5},"depth":2,"link":{"mindmap":{"uuid":""}},"relation":{"name":""}}],"width":144,"height":33,"position":{"x":-197,"y":-101.25},"depth":1,"link":{"mindmap":{"uuid":""}},"relation":{"name":""}},{"id":"16f3bde0-ad3e-417e-8ece-e1c237fde6d7","content":"Value vs Waste","type":"custom","deletable":true,"children":[{"id":"0cc2dba6-24d7-4345-b944-6d4b28dddd31","content":"Segala sesuatu yang bukan value","type":"custom","deletable":true,"children":[],"width":179,"height":33,"position":{"x":-427,"y":0},"depth":2,"link":{"mindmap":{"uuid":""}},"relation":{"name":""}}],"width":144,"height":33,"position":{"x":-197,"y":0},"depth":1,"link":{"mindmap":{"uuid":""}},"relation":{"name":""}},{"id":"31f1c4ff-aa6b-4432-a755-433fd6f8d956","content":"mvp","type":"custom","deletable":true,"children":[{"id":"4c67c355-e1d8-4696-87c2-ef0c3cc0177d","content":"minimum","type":"custom","deletable":true,"children":[{"id":"e71fce89-aa39-4d01-a403-0e5b9aa08def","content":"Fitur\/modul paling mendasar","type":"custom","deletable":true,"children":[],"width":158,"height":33,"position":{"x":-603,"y":45},"depth":3,"link":{"mindmap":{"uuid":""}},"relation":{"name":""}}],"width":144,"height":33,"position":{"x":-394,"y":45},"depth":2,"link":{"mindmap":{"uuid":""}},"relation":{"name":""}},{"id":"07364545-4b99-4e78-8940-626266333b8d","content":"Variable","type":"custom","deletable":true,"children":[{"id":"d475a86d-07cb-40ae-9385-5e3a4929e77b","content":"Bekerja dan dapat diuji coba","type":"custom","deletable":true,"children":[],"width":154,"height":33,"position":{"x":-599,"y":90},"depth":3,"link":{"mindmap":{"uuid":""}},"relation":{"name":""}}],"width":144,"height":33,"position":{"x":-394,"y":90},"depth":2,"link":{"mindmap":{"uuid":""}},"relation":{"name":""}},{"id":"d520aeea-7c73-407e-a769-5191566d6214","content":"Product","type":"custom","deletable":true,"children":[{"id":"0f690246-c8e1-424f-9919-8dc4e66b7830","content":"Berupa kendaraan nilai(value)","type":"custom","deletable":true,"children":[],"width":162,"height":33,"position":{"x":-653,"y":135},"depth":3,"link":{"mindmap":{"uuid":""}},"relation":{"name":""}}],"width":144,"height":33,"position":{"x":-394,"y":135},"depth":2,"link":{"mindmap":{"uuid":""}},"relation":{"name":""}}],"width":144,"height":33,"position":{"x":-197,"y":90},"depth":1,"link":{"mindmap":{"uuid":""}},"relation":{"name":""}}],"width":166,"height":33,"position":{"x":0,"y":0},"depth":0,"link":{"mindmap":{"uuid":""}}}],"version":2}