{"root":[{"id":"root","content":"[Review] Agile Transformation","type":"root","deletable":false,"children":[{"id":"42c2d66c-d3bb-41ac-8fcc-b01ed024a56d","content":"menjadi tim yang lincah dan tidak bosan","type":"custom","deletable":true,"children":[{"id":"b480100c-dcb9-42fe-9bfe-887f302ab469","content":"kita hidup di vuca word","type":"custom","deletable":true,"children":[{"id":"ff8a44cf-d6eb-4f4a-8f1d-cec956c77f42","content":"volatile","type":"custom","deletable":true,"children":[{"id":"9f2fb19e-2fbc-474e-961a-68b4038a4ab6","content":"perubahan yang cepat","type":"custom","deletable":true,"children":[{"id":"0e7074e8-a7ef-4d65-b890-16c4de237e65","content":"teknologi-trend pasar-kebutuhan pelanggan","type":"custom","deletable":true,"children":[],"width":235,"height":33,"position":{"x":1114,"y":-112.5},"depth":5,"link":{"mindmap":{"uuid":""}},"relation":{"name":""}}],"width":144,"height":33,"position":{"x":919,"y":-112.5},"depth":4,"link":{"mindmap":{"uuid":""}},"relation":{"name":""}}],"width":144,"height":33,"position":{"x":724,"y":-112.5},"depth":3,"link":{"mindmap":{"uuid":""}},"relation":{"name":""}},{"id":"ad29a068-75c1-4ec8-a9e3-0c9a5eb02aff","content":"uncertain","type":"custom","deletable":true,"children":[{"id":"8611a2fc-dda0-4b2e-ba75-31c0ad19328d","content":"tidak pasti","type":"custom","deletable":true,"children":[{"id":"69627f38-e4bc-436c-b600-a42ca7b7bb23","content":"perubahan tanpa pemberitahuan","type":"custom","deletable":true,"children":[],"width":176,"height":33,"position":{"x":1114,"y":-67.5},"depth":5,"link":{"mindmap":{"uuid":""}},"relation":{"name":""}}],"width":144,"height":33,"position":{"x":919,"y":-67.5},"depth":4,"link":{"mindmap":{"uuid":""}},"relation":{"name":""}}],"width":144,"height":33,"position":{"x":724,"y":-67.5},"depth":3,"link":{"mindmap":{"uuid":""}},"relation":{"name":""}},{"id":"fe1437e4-be19-4891-896d-d2dc98ab415e","content":"complex","type":"custom","deletable":true,"children":[{"id":"5dc6b290-e440-4d38-af83-50a842874aa3","content":"kompleksitas","type":"custom","deletable":true,"children":[{"id":"8b281099-fd4c-4d23-b0c9-19f5704a7883","content":"tidak bisa dipecahkan dengan sederhana","type":"custom","deletable":true,"children":[{"id":"6d7430dc-40b7-4f76-8d18-87404da41dd9","content":"banyak faktor yang mempengaruhinya","type":"custom","deletable":true,"children":[],"width":205,"height":33,"position":{"x":1383,"y":-22.5},"depth":6,"link":{"mindmap":{"uuid":""}},"relation":{"name":""}}],"width":218,"height":33,"position":{"x":1114,"y":-22.5},"depth":5,"link":{"mindmap":{"uuid":""}},"relation":{"name":""}}],"width":144,"height":33,"position":{"x":919,"y":-22.5},"depth":4,"link":{"mindmap":{"uuid":""}},"relation":{"name":""}}],"width":144,"height":33,"position":{"x":724,"y":-22.5},"depth":3,"link":{"mindmap":{"uuid":""}},"relation":{"name":""}},{"id":"d8aa92bf-e921-4d58-a214-a9b268fc9dc1","content":"ambigous","type":"custom","deletable":true,"children":[{"id":"8c561094-ebb9-44b3-99df-6a08432db889","content":"ambigu\/bermakna ganda","type":"custom","deletable":true,"children":[],"width":144,"height":33,"position":{"x":919,"y":22.5},"depth":4,"link":{"mindmap":{"uuid":""}},"relation":{"name":""}}],"width":144,"height":33,"position":{"x":724,"y":22.5},"depth":3,"link":{"mindmap":{"uuid":""}},"relation":{"name":""}}],"width":144,"height":33,"position":{"x":526,"y":-45},"depth":2,"link":{"mindmap":{"uuid":""}},"relation":{"name":""}}],"width":215,"height":33,"position":{"x":260,"y":-45},"depth":1,"link":{"mindmap":{"uuid":""}},"relation":{"name":""}},{"id":"f754111b-b3ad-4763-9633-b2abba9c7085","content":"metode lawas dengan waterfall seperti air terjun","type":"custom","deletable":true,"children":[{"id":"1adf7b03-6a36-4350-8f31-c79669822a26","content":"setiap tingkat harus selesai berurutan","type":"custom","deletable":true,"children":[{"id":"89aaa8ec-eef9-4c43-8f89-929b90be8609","content":"sehingga terjadi saling tungu-menuggu","type":"custom","deletable":true,"children":[],"width":210,"height":33,"position":{"x":821,"y":67.5},"depth":3,"link":{"mindmap":{"uuid":""}},"relation":{"name":""}}],"width":203,"height":33,"position":{"x":567,"y":67.5},"depth":2,"link":{"mindmap":{"uuid":""}},"relation":{"name":""}}],"width":256,"height":33,"position":{"x":260,"y":67.5},"depth":1,"link":{"mindmap":{"uuid":""}},"relation":{"name":""}},{"id":"43d1b363-d595-4a6e-88e5-f889e038206a","content":"agile","type":"custom","deletable":true,"children":[{"id":"068b4fb7-fa3c-4260-a9ff-4ef861ad6d5e","content":"cocok untuk pengembangan produk","type":"custom","deletable":true,"children":[],"width":193,"height":33,"position":{"x":455,"y":112.5},"depth":2,"link":{"mindmap":{"uuid":""}},"relation":{"name":""}}],"width":144,"height":33,"position":{"x":260,"y":112.5},"depth":1,"link":{"mindmap":{"uuid":""}},"relation":{"name":""}},{"id":"fa2ad0a3-bbc8-4819-8187-15f61b6e174b","content":"perubahan dari tradisional menjadi agile","type":"custom","deletable":true,"children":[{"id":"17696645-1eeb-4f60-9593-42c56d9673e5","content":"manfaat","type":"custom","deletable":true,"children":[{"id":"55dd9c2a-f9fd-4cd9-ae4a-9ca7275783b4","content":"tim makin jago","type":"custom","deletable":true,"children":[],"width":144,"height":33,"position":{"x":-659,"y":-67.5},"depth":3,"link":{"mindmap":{"uuid":""}},"relation":{"name":""}},{"id":"fbefd2aa-b1a5-4ea6-b502-42570e3d30a6","content":"produk lebih bernilai","type":"custom","deletable":true,"children":[],"width":144,"height":33,"position":{"x":-659,"y":-22.5},"depth":3,"link":{"mindmap":{"uuid":""}},"relation":{"name":""}},{"id":"259a4b44-c66d-4ecc-8510-93e35056448f","content":"hemat biaya","type":"custom","deletable":true,"children":[],"width":144,"height":33,"position":{"x":-659,"y":22.5},"depth":3,"link":{"mindmap":{"uuid":""}},"relation":{"name":""}},{"id":"22dd776f-8dcc-4e48-a0e2-4c0da9355790","content":"produk rilis lebih awal","type":"custom","deletable":true,"children":[],"width":144,"height":33,"position":{"x":-664,"y":67.5},"depth":3,"link":{"mindmap":{"uuid":""}},"relation":{"name":""}}],"width":144,"height":33,"position":{"x":-461,"y":0},"depth":2,"link":{"mindmap":{"uuid":""}},"relation":{"name":""}}],"width":215,"height":33,"position":{"x":-266,"y":0},"depth":1,"link":{"mindmap":{"uuid":""}},"relation":{"name":""}}],"width":207,"height":33,"position":{"x":0,"y":0},"depth":0,"link":{"mindmap":{"uuid":""}}}],"version":2}