{"root":[{"id":"root","content":"Fixed Mindset vs Agile Mindset","type":"root","deletable":false,"children":[{"id":"29b07234-979d-4914-b6bc-6288eff14877","content":"Fixed Mindset","type":"custom","deletable":true,"children":[{"id":"e901d9cf-cc1d-4866-81d2-618d50e3b4ca","content":"Kemampuam tidak dapat diubah","type":"custom","deletable":true,"children":[],"width":176,"height":34,"position":{"x":469,"y":-247.5},"depth":2,"link":{"mindmap":{"uuid":""}},"relation":{"name":""}},{"id":"0efe914e-b371-4cdc-aee3-7124ad940eae","content":"Melakukan sesuatu supaya terlihat baik","type":"custom","deletable":true,"children":[],"width":213,"height":34,"position":{"x":469,"y":-202.5},"depth":2,"link":{"mindmap":{"uuid":""}},"relation":{"name":""}},{"id":"534f4bd6-3bed-4b8f-9930-bafe5261b502","content":"Menghindari tantangan","type":"custom","deletable":true,"children":[],"width":145,"height":34,"position":{"x":469,"y":-157.5},"depth":2,"link":{"mindmap":{"uuid":""}},"relation":{"name":""}},{"id":"e5c434ae-d94d-423b-9a3d-ab8960005829","content":"Kegagalan dianggap sebagai aib","type":"custom","deletable":true,"children":[],"width":176,"height":34,"position":{"x":469,"y":-112.5},"depth":2,"link":{"mindmap":{"uuid":""}},"relation":{"name":""}},{"id":"d0e48b33-3a20-4ad5-bad7-d6a8db9e86f5","content":"Usaha dikalaukan orang yang didakmemiliki bakat","type":"custom","deletable":true,"children":[],"width":267,"height":34,"position":{"x":469,"y":-67.5},"depth":2,"link":{"mindmap":{"uuid":""}},"relation":{"name":""}},{"id":"a44ebdaa-840f-48b1-93c3-00bfe0278219","content":"Tidak erdaya apabila ada tantangan","type":"custom","deletable":true,"children":[],"width":192,"height":34,"position":{"x":469,"y":-22.5},"depth":2,"link":{"mindmap":{"uuid":""}},"relation":{"name":""}}],"width":145,"height":34,"position":{"x":268,"y":-135},"depth":1,"link":{"mindmap":{"uuid":""}},"relation":{"name":""}},{"id":"064ec2cb-19b1-4fde-b24e-9b98c78a44e4","content":"Agile Mindset","type":"custom","deletable":true,"children":[{"id":"768fd4e1-89fa-43b6-b074-29f88cc95218","content":"Kemampuan dapat diasah kapan pun","type":"custom","deletable":true,"children":[],"width":199,"height":34,"position":{"x":469,"y":22.5},"depth":2,"link":{"mindmap":{"uuid":""}},"relation":{"name":""}},{"id":"4713388f-90bd-4053-8d76-65aabfef6cf2","content":"Melakukan sesuatu untuk mengukur kemampuan","type":"custom","deletable":true,"children":[],"width":262,"height":34,"position":{"x":469,"y":67.5},"depth":2,"link":{"mindmap":{"uuid":""}},"relation":{"name":""}},{"id":"a43ff844-6501-4208-9a57-c7c39b3a185a","content":"Suka tantangan","type":"custom","deletable":true,"children":[],"width":145,"height":34,"position":{"x":469,"y":112.5},"depth":2,"link":{"mindmap":{"uuid":""}},"relation":{"name":""}},{"id":"1da7fbac-679e-4416-b5a4-daa3eeda377d","content":"Kegagalan dianggap sebagai pembelajaran","type":"custom","deletable":true,"children":[],"width":230,"height":34,"position":{"x":469,"y":157.5},"depth":2,"link":{"mindmap":{"uuid":""}},"relation":{"name":""}},{"id":"a15c6896-79b7-4438-921f-de6ac3d55982","content":"Selalu berusaha apapun alasanya","type":"custom","deletable":true,"children":[],"width":181,"height":34,"position":{"x":469,"y":202.5},"depth":2,"link":{"mindmap":{"uuid":""}},"relation":{"name":""}},{"id":"1354a975-6924-4b5c-9cf1-a089862995de","content":"Mencari solusi untuk menyelesaikan tantangan","type":"custom","deletable":true,"children":[],"width":251,"height":34,"position":{"x":469,"y":247.5},"depth":2,"link":{"mindmap":{"uuid":""}},"relation":{"name":""}}],"width":145,"height":34,"position":{"x":268,"y":135},"depth":1,"link":{"mindmap":{"uuid":""}},"relation":{"name":""}}],"width":216,"height":34,"position":{"x":0,"y":0},"depth":0,"link":{"mindmap":{"uuid":""}}}],"version":2}