{"root":[{"id":"root","content":"[Review] Agile Fundamentals","type":"root","deletable":false,"children":[{"id":"a1986bcd-979c-4f45-87ae-c07a52a01c38","content":"model dari ahmad sidky","type":"custom","deletable":true,"children":[{"id":"6d2a11c4-ba33-416b-a562-d2e1a7fef4f5","content":"agile mindset","type":"custom","deletable":true,"children":[{"id":"908211ed-2911-4eb6-bd99-332928184f80","content":"memiliki 4 values (agile manifesto)","type":"custom","deletable":true,"children":[{"id":"ad8383fa-dcc8-49ef-aa81-8fdfab053b63","content":"panduan lebih rinci berupa agile principle","type":"custom","deletable":true,"children":[{"id":"f707945c-3803-4378-90c2-6c501d398811","content":"praktek dari agile, seperti scrum, kanban, dll","type":"custom","deletable":true,"children":[],"width":237,"height":34,"position":{"x":1160,"y":0},"depth":5,"link":{"mindmap":{"uuid":""}},"relation":{"name":""}}],"width":221,"height":34,"position":{"x":888,"y":0},"depth":4,"link":{"mindmap":{"uuid":""}},"relation":{"name":""}}],"width":190,"height":34,"position":{"x":643,"y":0},"depth":3,"link":{"mindmap":{"uuid":""}},"relation":{"name":""}}],"width":145,"height":34,"position":{"x":447,"y":0},"depth":2,"link":{"mindmap":{"uuid":""}},"relation":{"name":""}}],"width":145,"height":34,"position":{"x":251,"y":0},"depth":1,"link":{"mindmap":{"uuid":""}},"relation":{"name":""}}],"width":200,"height":34,"position":{"x":0,"y":0},"depth":0,"link":{"mindmap":{"uuid":""}}}],"version":2}